{
  "name": "Beauty Ulrich",
  "ai": {
    "type": "rct",
    "data": {
      "maxSelectMargin": 0.13953814366525205
    }
  },
  "battleRules": {
    "maxItemUses": 4
  },
  "bag": [
    {
      "item": "cobblemon:superb_remedy",
      "quantity": 2
    }
  ],
  "team": [
    {
      "species": "volcarona",
      "gender": "MALE",
      "level": 28,
      "nature": "serious",
      "ability": "rockhead",
      "moveset": [
        "solarbeam",
        "willowisp",
        "crunch",
        "megapunch"
      ],
      "ivs": {},
      "evs": {}
    },
    {
      "species": "vaporeon",
      "gender": "FEMALE",
      "level": 33,
      "nature": "calm",
      "ability": "immunity",
      "moveset": [
        "willowisp",
        "zenheadbutt",
        "dragonpulse",
        "megapunch"
      ],
      "ivs": {},
      "evs": {}
    },
    {
      "species": "mamoswine",
      "gender": "MALE",
      "level": 27,
      "nature": "adamant",
      "ability": "torrent",
      "moveset": [
        "stoneedge",
        "zenheadbutt",
        "growth",
        "airslash"
      ],
      "ivs": {},
      "evs": {}
    },
    {
      "species": "ekans",
      "gender": "FEMALE",
      "level": 25,
      "nature": "calm",
      "ability": "immunity",
      "moveset": [
        "recover",
        "surf",
        "megakick",
        "shadowclaw"
      ],
      "ivs": {},
      "evs": {}
    },
    {
      "species": "geodude",
      "gender": "FEMALE",
      "level": 32,
      "nature": "modest",
      "ability": "swarm",
      "moveset": [
        "stealthrock",
        "bodyslam",
        "crunch",
        "fireblast"
      ],
      "ivs": {},
      "evs": {}
    }
  ]
}