{
  "name": "Veteran George",
  "trainer_class": "VETERAN",
  "win_money_base": 1505,
  "ai": {
    "intelligence": 0.8,
    "switch_chance": 0.6
  },
  "team": [
    {
      "pokemon": "tyranitar",
      "level": 66,
      "gender": "female",
      "moves": [
        "tackle",
        "scratch",
        "pound",
        "quickattack"
      ],
      "ability": "magicguard",
      "nature": "adamant",
      "evs": {
        "hp": 252,
        "attack": 252,
        "defense": 0,
        "special_attack": 0,
        "special_defense": 4,
        "speed": 252
      },
      "ivs": {
        "hp": 31,
        "attack": 31,
        "defense": 31,
        "special_attack": 31,
        "special_defense": 31,
        "speed": 31
      },
      "held_item": "lumberry"
    },
    {
      "pokemon": "goodra",
      "level": 66,
      "gender": "female",
      "moves": [
        "tackle",
        "scratch",
        "pound",
        "quickattack"
      ],
      "ability": "flashfire",
      "nature": "modest",
      "evs": {
        "hp": 252,
        "attack": 252,
        "defense": 0,
        "special_attack": 0,
        "special_defense": 4,
        "speed": 252
      },
      "ivs": {
        "hp": 31,
        "attack": 31,
        "defense": 31,
        "special_attack": 31,
        "special_defense": 31,
        "speed": 31
      },
      "held_item": "leftovers"
    },
    {
      "pokemon": "metagross",
      "level": 67,
      "gender": "male",
      "moves": [
        "tackle",
        "scratch",
        "pound",
        "quickattack"
      ],
      "ability": "swarm",
      "nature": "adamant",
      "evs": {
        "hp": 252,
        "attack": 252,
        "defense": 0,
        "special_attack": 0,
        "special_defense": 4,
        "speed": 252
      },
      "ivs": {
        "hp": 31,
        "attack": 31,
        "defense": 31,
        "special_attack": 31,
        "special_defense": 31,
        "speed": 31
      },
      "held_item": "lifeorb"
    },
    {
      "pokemon": "grapploct",
      "level": 68,
      "gender": "male",
      "moves": [
        "tackle",
        "scratch",
        "pound",
        "quickattack"
      ],
      "ability": "flashfire",
      "nature": "careful",
      "evs": {
        "hp": 252,
        "attack": 252,
        "defense": 0,
        "special_attack": 0,
        "special_defense": 4,
        "speed": 252
      },
      "ivs": {
        "hp": 31,
        "attack": 31,
        "defense": 31,
        "special_attack": 31,
        "special_defense": 31,
        "speed": 31
      },
      "held_item": "assaultvest"
    }
  ],
  "bag": [
    {
      "item": "cobblemon:max_potion",
      "count": 2
    }
  ],
  "defeat_actions": [
    {
      "type": "give_money",
      "amount": 3010
    },
    {
      "type": "give_exp",
      "multiplier": 1.67
    },
    {
      "type": "give_item",
      "item": "cobblemon:rare_candy",
      "count": 2
    }
  ]
}