{
  "name": "Picnicker Nathan",
  "ai": {
    "type": "rct",
    "data": {
      "maxSelectMargin": 0.13785682207577094
    }
  },
  "battleRules": {
    "maxItemUses": 2
  },
  "bag": [
    {
      "item": "cobblemon:superb_remedy",
      "quantity": 2
    }
  ],
  "team": [
    {
      "species": "bulbasaur",
      "gender": "FEMALE",
      "level": 26,
      "nature": "quirky",
      "ability": "keeneye",
      "moveset": [
        "doubleedge",
        "takedown",
        "substitute",
        "thunderbolt"
      ],
      "ivs": {},
      "evs": {}
    },
    {
      "species": "oddish",
      "gender": "FEMALE",
      "level": 26,
      "nature": "docile",
      "ability": "soundproof",
      "moveset": [
        "fireblast",
        "outrage",
        "stunspore",
        "scratch"
      ],
      "ivs": {},
      "evs": {}
    },
    {
      "species": "regirock",
      "gender": "MALE",
      "level": 22,
      "nature": "gentle",
      "ability": "swarm",
      "moveset": [
        "confusion",
        "recover",
        "icepunch",
        "closecombat"
      ],
      "ivs": {},
      "evs": {}
    }
  ]
}